LICENSE.txt
MANIFEST.in
README.md
setup.py
lt/__init__.py
lt/sampler.py
lt/decode/__init__.py
lt/decode/__main__.py
lt/encode/__init__.py
lt/encode/__main__.py
lt_code.egg-info/PKG-INFO
lt_code.egg-info/SOURCES.txt
lt_code.egg-info/dependency_links.txt
lt_code.egg-info/top_level.txt