Metadata-Version: 1.0
Name: lt-code
Version: 0.3.1
Summary: An implementation of an Encoder and Decoder for the Luby Transform Fountain code. Useful for transmitting data over very lossy channels where retry-based transmission protocols struggle.
Home-page: https://github.com/anrosent/LT-Code
Author: Anson Rosenthal
Author-email: anson.rosenthal@gmail.com
License: UNKNOWN
Platform: UNKNOWN
